SQLAlchemy_wrap/__init__.py
SQLAlchemy_wrap/exceptions/__init__.py
SQLAlchemy_wrap/exceptions/connect_error.py
SQLAlchemy_wrap/exceptions/db_not_connect.py
SQLAlchemy_wrap/exceptions/no_table_operator_class_exception.py
SQLAlchemy_wrap/interfaces/__init__.py
SQLAlchemy_wrap/interfaces/i_db_factory.py
SQLAlchemy_wrap/interfaces/i_project.py
SQLAlchemy_wrap/interfaces/i_table.py
SQLAlchemy_wrap/sql_factory/__init__.py
SQLAlchemy_wrap/sql_factory/base_table.py
SQLAlchemy_wrap/sql_factory/mysql_factory.py
SQLAlchemy_wrap/sql_factory/sqlalchemy_factory.py
SQLAlchemy_wrap/sql_factory/sqlite_factory.py
tests/table_class/__init__.py
tests/table_class/unittest/__init__.py
tests/table_class/unittest/unittest_table.py
tests/table_class/unittest/use_exists_table.py
SQLAlchemy_wrap-2.1.7.dist-info/METADATA
SQLAlchemy_wrap-2.1.7.dist-info/WHEEL
SQLAlchemy_wrap-2.1.7.dist-info/top_level.txt
SQLAlchemy_wrap-2.1.7.dist-info/RECORD
