Metadata-Version: 2.1
Name: SQLAlchemy-wrap
Version: 2.1.7
Summary: Python wrapper for the CircleCI API
Home-page: https://github.com/Jefung/SQLAlchemy_wrap
Author: Jefung
Author-email: 865424525@qq.com
License: MIT
Keywords: circleci ci cd api sdk
Platform: UNKNOWN
Classifier: Development Status :: 5 - Production/Stable
Classifier: Intended Audience :: Developers
Classifier: Intended Audience :: System Administrators
Classifier: License :: OSI Approved :: MIT License
Classifier: Operating System :: OS Independent
Classifier: Topic :: Software Development :: Build Tools
Classifier: Topic :: Software Development :: Libraries :: Python Modules
Classifier: Topic :: Internet
Classifier: Programming Language :: Python :: 3
Requires-Dist: requests (==2.18.4)
